pysteve/__init__.py
pysteve/pySteve.py
pysteve-0.0.18.dist-info/LICENSE
pysteve-0.0.18.dist-info/METADATA
pysteve-0.0.18.dist-info/WHEEL
pysteve-0.0.18.dist-info/top_level.txt
pysteve-0.0.18.dist-info/RECORD
