Metadata-Version: 2.1
Name: pysteve
Version: 0.0.18
Summary: Helper and setup functions for people named Steve
Author-email: Stephen Hilton <Stephen@FamilyHilton.com>
License: MIT License
Project-URL: Homepage, https://familyhilton.com
Project-URL: Docs, https://github.com/Stephen-Hilton/pysteve/blob/main/README.md
Project-URL: Documentation, https://github.com/Stephen-Hilton/pysteve/blob/main/README.md
Project-URL: Github, https://github.com/Stephen-Hilton/pysteve
Keywords: helper,setup,boilerplate,data
Classifier: License :: OSI Approved :: MIT License
Classifier: Programming Language :: Python
Classifier: Programming Language :: Python :: 3
Requires-Python: >=3.10
License-File: LICENSE
Requires-Dist: requests >=2.31.0
Provides-Extra: dev
Requires-Dist: pip-tools ; extra == 'dev'
Requires-Dist: pytest ; extra == 'dev'
